mlx_embeddings_lora/__init__.py
mlx_embeddings_lora/__main__.py
mlx_embeddings_lora/train.py
mlx_embeddings_lora/version.py
mlx_embeddings_lora/trainer/__init__.py
mlx_embeddings_lora/trainer/contrastive_trainer.py
mlx_embeddings_lora/trainer/dataset.py
mlx_embeddings_lora/trainer/lora.py
mlx_embeddings_lora/trainer/utils.py
mlx_embeddings_lora-1.0.5.dist-info/licenses/LICENSE
mlx_embeddings_lora-1.0.5.dist-info/METADATA
mlx_embeddings_lora-1.0.5.dist-info/WHEEL
mlx_embeddings_lora-1.0.5.dist-info/entry_points.txt
mlx_embeddings_lora-1.0.5.dist-info/top_level.txt
mlx_embeddings_lora-1.0.5.dist-info/RECORD
