Metadata-Version: 2.4
Name: mlx-embeddings-lora
Version: 1.0.5
Summary: Train Embedding Models on Apple silicon with MLX and the Hugging Face Hub
Home-page: https://github.com/Goekdeniz-Guelmez/mlx-embeddings-lora
Author: Gökdeniz Gülmez
Author-email: goekdenizguelmez@gmail.com
License: MIT
Requires-Python: >=3.8
License-File: LICENSE
Requires-Dist: mlx>=0.29.3
Requires-Dist: mlx_lm>=0.28.3
Requires-Dist: transformers>=4.39.3
Requires-Dist: protobuf
Requires-Dist: pyyaml
Requires-Dist: jinja2
Requires-Dist: tqdm
Requires-Dist: datasets
Requires-Dist: mlx-embeddings>=0.0.5
Dynamic: author
Dynamic: author-email
Dynamic: description
Dynamic: description-content-type
Dynamic: home-page
Dynamic: license
Dynamic: license-file
Dynamic: requires-dist
Dynamic: requires-python
Dynamic: summary
